threedeploy/__init__.py
threedeploy/__main__.py
threedeploy/threedeploy.py
threedeploy-1.1.0.dist-info/LICENSE
threedeploy-1.1.0.dist-info/METADATA
threedeploy-1.1.0.dist-info/WHEEL
threedeploy-1.1.0.dist-info/entry_points.txt
threedeploy-1.1.0.dist-info/top_level.txt
threedeploy-1.1.0.dist-info/RECORD
