Metadata-Version: 2.2
Name: threedeploy
Version: 1.1.0
Summary: Automatically deploy your 3d projects to multiple sites like Prusaprinters, Thangs, or even Thingiverse!
Home-page: https://gitlab.com/chrismettal/threedeploy
Author: chrismettal
Author-email: chrismettal@binary-6.de
Classifier: Programming Language :: Python :: 3
Classifier: License :: OSI Approved :: GNU General Public License v3 or later (GPLv3+)
Classifier: Operating System :: OS Independent
Requires-Python: >=3.6
License-File: LICENSE
Requires-Dist: DateTime~=4.3
Requires-Dist: requests~=2.32.3
Requires-Dist: pyyaml~=6.0.2
